integration/__init__.py
integration/helper.py
integration/test_sen2.py
integration/test_sen3.py
tests/helpers/__init__.py
tests/helpers/sentinel2.py
tests/helpers/sentinel3.py
tests/prodhandlers/__init__.py
tests/prodhandlers/test_sentinel_2.py
tests/prodhandlers/test_sentinel_3.py
xcube_eopf/__init__.py
xcube_eopf/constants.py
xcube_eopf/plugin.py
xcube_eopf/prodhandler.py
xcube_eopf/store.py
xcube_eopf/utils.py
xcube_eopf/version.py
xcube_eopf/prodhandlers/__init__.py
xcube_eopf/prodhandlers/sentinel1.py
xcube_eopf/prodhandlers/sentinel2.py
xcube_eopf/prodhandlers/sentinel3.py
xcube_eopf-0.3.0.dist-info/licenses/LICENSE
xcube_eopf-0.3.0.dist-info/METADATA
xcube_eopf-0.3.0.dist-info/WHEEL
xcube_eopf-0.3.0.dist-info/top_level.txt
xcube_eopf-0.3.0.dist-info/RECORD
