Metadata-Version: 2.4
Name: xcube-eopf
Version: 0.3.0
Summary: xcube datastore for accessing datasets of ESA EOPF data products.
Author: Konstantin Ntokas (Brockmann Consult GmbH), Norman Fomferra (Brockmann Consult GmbH)
License: Apache-2.0
Project-URL: Documentation, https://eopf-sample-service.github.io/xcube-eopf
Project-URL: Repository, https://github.com/EOPF-Sample-Service/xcube-eopf
Project-URL: Changelog, https://github.com/EOPF-Sample-Service/xcube-eopf/blob/main/CHANGES.md
Project-URL: Issues, https://github.com/EOPF-Sample-Service/xcube-eopf/issues
Keywords: copernicus,esa,eopf,sentinel,xarray,zarr
Classifier: Development Status :: 5 - Production/Stable
Classifier: Intended Audience :: Science/Research
Classifier: Intended Audience :: Developers
Classifier: License :: OSI Approved :: Apache Software License
Classifier: Programming Language :: Python :: 3
Classifier: Programming Language :: Python :: 3.10
Classifier: Programming Language :: Python :: 3.11
Classifier: Programming Language :: Python :: 3.12
Classifier: Programming Language :: Python :: 3.13
Classifier: Topic :: Software Development
Classifier: Topic :: Scientific/Engineering
Classifier: Typing :: Typed
Classifier: Operating System :: Microsoft :: Windows
Classifier: Operating System :: POSIX
Classifier: Operating System :: Unix
Classifier: Operating System :: MacOS
Requires-Python: >=3.10
License-File: LICENSE
Requires-Dist: dask
Requires-Dist: numpy
Requires-Dist: pyproj
Requires-Dist: pystac
Requires-Dist: pystac-client
Requires-Dist: shapely
Requires-Dist: xarray
Requires-Dist: xarray-eopf>=0.2.0
Requires-Dist: xcube-core>=1.11.0
Requires-Dist: xcube-resampling>=0.1.1
Provides-Extra: dev
Requires-Dist: build; extra == "dev"
Requires-Dist: hatch; extra == "dev"
Requires-Dist: twine; extra == "dev"
Requires-Dist: black; extra == "dev"
Requires-Dist: isort; extra == "dev"
Requires-Dist: ruff; extra == "dev"
Requires-Dist: pytest; extra == "dev"
Requires-Dist: pytest-cov; extra == "dev"
Requires-Dist: pytest-recording; extra == "dev"
Requires-Dist: jupyterlab; extra == "dev"
Requires-Dist: matplotlib; extra == "dev"
Provides-Extra: doc
Requires-Dist: mkdocs; extra == "doc"
Requires-Dist: mkdocs-autorefs; extra == "doc"
Requires-Dist: mkdocs-material; extra == "doc"
Requires-Dist: mkdocstrings; extra == "doc"
Requires-Dist: mkdocstrings-python; extra == "doc"
Dynamic: license-file
